abjadtools
